app/__init__.py
app/main.py
app/ext/__init__.py
app/ext/extension.py
app/modules/__init__.py
app/modules/configs.py
app/modules/session.py
async_db_alchemy-0.1.0.dist-info/METADATA
async_db_alchemy-0.1.0.dist-info/WHEEL
async_db_alchemy-0.1.0.dist-info/licenses/LICENSE
async_db_alchemy-0.1.0.dist-info/RECORD
