Metadata-Version: 2.4
Name: async-db-alchemy
Version: 0.1.0
Summary: Async SQLAlchemy utilities
Author-email: KyungHo Kim <qqaa3030@gmail.com>
License: MIT
License-File: LICENSE
Classifier: License :: OSI Approved :: MIT License
Classifier: Programming Language :: Python :: 3.11
Requires-Python: >=3.11
Requires-Dist: asyncpg>=0.30.0
Requires-Dist: greenlet>=3.1.1
Requires-Dist: pydantic>=2.10.5
Requires-Dist: sqlalchemy>=2.0.37
